{"serchcode": "\u7206\u4e73\u5fb5\u4fe1\u793e\u54e1\u5de5\uff0d\u71d9\u71d9Leona", "host": "https://www.jkforum.net/thread-9250354-1-5.html", "auth": "", "personnel": "", "title": "\u7206\u4e73\u5fb5\u4fe1\u793e\u54e1\u5de5,\u71d9\u71d9,\u5973\u90ce,\u6377\u514b\u8ad6\u58c7", "series": "", "img": ["./images/JKF_girls/\u7206\u4e73\u5fb5\u4fe1\u793e\u54e1\u5de5\uff0d\u71d9\u71d9LeonaJKF\u5973\u90ce/1.png", "./images/JKF_girls/\u7206\u4e73\u5fb5\u4fe1\u793e\u54e1\u5de5\uff0d\u71d9\u71d9LeonaJKF\u5973\u90ce/2.png", "./images/JKF_girls/\u7206\u4e73\u5fb5\u4fe1\u793e\u54e1\u5de5\uff0d\u71d9\u71d9LeonaJKF\u5973\u90ce/3.png", "./images/JKF_girls/\u7206\u4e73\u5fb5\u4fe1\u793e\u54e1\u5de5\uff0d\u71d9\u71d9LeonaJKF\u5973\u90ce/4.png", "./images/JKF_girls/\u7206\u4e73\u5fb5\u4fe1\u793e\u54e1\u5de5\uff0d\u71d9\u71d9LeonaJKF\u5973\u90ce/5.png", "./images/JKF_girls/\u7206\u4e73\u5fb5\u4fe1\u793e\u54e1\u5de5\uff0d\u71d9\u71d9LeonaJKF\u5973\u90ce/6.png", "./images/JKF_girls/\u7206\u4e73\u5fb5\u4fe1\u793e\u54e1\u5de5\uff0d\u71d9\u71d9LeonaJKF\u5973\u90ce/7.png", "./images/JKF_girls/\u7206\u4e73\u5fb5\u4fe1\u793e\u54e1\u5de5\uff0d\u71d9\u71d9LeonaJKF\u5973\u90ce/8.png", "./images/JKF_girls/\u7206\u4e73\u5fb5\u4fe1\u793e\u54e1\u5de5\uff0d\u71d9\u71d9LeonaJKF\u5973\u90ce/9.png", "./images/JKF_girls/\u7206\u4e73\u5fb5\u4fe1\u793e\u54e1\u5de5\uff0d\u71d9\u71d9LeonaJKF\u5973\u90ce/10.png", "./images/JKF_girls/\u7206\u4e73\u5fb5\u4fe1\u793e\u54e1\u5de5\uff0d\u71d9\u71d9LeonaJKF\u5973\u90ce/11.png", "./images/JKF_girls/\u7206\u4e73\u5fb5\u4fe1\u793e\u54e1\u5de5\uff0d\u71d9\u71d9LeonaJKF\u5973\u90ce/12.png", "./images/JKF_girls/\u7206\u4e73\u5fb5\u4fe1\u793e\u54e1\u5de5\uff0d\u71d9\u71d9LeonaJKF\u5973\u90ce/13.png", "./images/JKF_girls/\u7206\u4e73\u5fb5\u4fe1\u793e\u54e1\u5de5\uff0d\u71d9\u71d9LeonaJKF\u5973\u90ce/14.png", "./images/JKF_girls/\u7206\u4e73\u5fb5\u4fe1\u793e\u54e1\u5de5\uff0d\u71d9\u71d9LeonaJKF\u5973\u90ce/15.png", "./images/JKF_girls/\u7206\u4e73\u5fb5\u4fe1\u793e\u54e1\u5de5\uff0d\u71d9\u71d9LeonaJKF\u5973\u90ce/16.png", "./images/JKF_girls/\u7206\u4e73\u5fb5\u4fe1\u793e\u54e1\u5de5\uff0d\u71d9\u71d9LeonaJKF\u5973\u90ce/17.png", "./images/JKF_girls/\u7206\u4e73\u5fb5\u4fe1\u793e\u54e1\u5de5\uff0d\u71d9\u71d9LeonaJKF\u5973\u90ce/18.png", "./images/JKF_girls/\u7206\u4e73\u5fb5\u4fe1\u793e\u54e1\u5de5\uff0d\u71d9\u71d9LeonaJKF\u5973\u90ce/19.png", "./images/JKF_girls/\u7206\u4e73\u5fb5\u4fe1\u793e\u54e1\u5de5\uff0d\u71d9\u71d9LeonaJKF\u5973\u90ce/20.png", "./images/JKF_girls/\u7206\u4e73\u5fb5\u4fe1\u793e\u54e1\u5de5\uff0d\u71d9\u71d9LeonaJKF\u5973\u90ce/21.png", "./images/JKF_girls/\u7206\u4e73\u5fb5\u4fe1\u793e\u54e1\u5de5\uff0d\u71d9\u71d9LeonaJKF\u5973\u90ce/22.png", "./images/JKF_girls/\u7206\u4e73\u5fb5\u4fe1\u793e\u54e1\u5de5\uff0d\u71d9\u71d9LeonaJKF\u5973\u90ce/23.png", "./images/JKF_girls/\u7206\u4e73\u5fb5\u4fe1\u793e\u54e1\u5de5\uff0d\u71d9\u71d9LeonaJKF\u5973\u90ce/24.png"], "img_rows": 24, "keywords": "jkfladys", "description": "\u9019\u6b21\u4ecb\u7d39\u4e00\u4f4d\u8d85\u7279\u5225\u7684\u6b63\u59b9\u71d9\u71d9Leona\uff0c\u4e00\u96d9\u6c34\u6c6a\u6c6a\u7684\u5927\u773c\u548c\u751c\u7f8e\u7b11\u5bb9\u8d85\u53ef\u611b\uff0c\u6c92\u60f3\u5230\u5979\u7adf\u7136\u6709\u706b\u8fa3\u7684E\u5976\u8eab\u6750\uff0c\u582a\u7a31\u5b8c\u7f8e\u7684\u689d\u4ef6\u8b93\u5979\u6210\u70ba\u5929\u83dc\u7d1a\u7684\u6b63\u59b9\uff0c\u800c\u4e14\u71d9\u71d9Leona\u9084\u66fe\u7d93\u5728\u5fb5", "section": [], "h1": "\u7206\u4e73\u5fb5\u4fe1\u793e\u54e1\u5de5\uff0d\u71d9\u71d9Leona", "title_main": "\u7206\u4e73\u5fb5\u4fe1\u793e\u54e1\u5de5\uff0d\u71d9\u71d9Leona - JKF\u5973\u90ce"}